{
  "categories": [
    "fight"
  ],
  "confidence": 67.13762879371643,
  "created_at": "2026-07-09T16:23:22",
  "detections": [
    {
      "box": [
        426,
        145,
        902,
        591
      ],
      "category": "fight",
      "confidence": 0.6713762879371643,
      "label": "fight"
    }
  ],
  "id": 1783590802816,
  "image_file": "ip-webcam-20260709-162322.jpg",
  "image_path": "image_data/ip-webcam-20260709-162322.jpg",
  "labels": [
    "fight"
  ],
  "location": "East Corridor",
  "notes": "fight",
  "status": "pending"
}